src/PySimpleGUI.py
src/__init__.py
src/main.py
src/qetproject.py
src/scroll_sample.py
src/terminalblock.py
qet_tb_generator-1.3.1.dist-info/LICENSE.txt
qet_tb_generator-1.3.1.dist-info/METADATA
qet_tb_generator-1.3.1.dist-info/WHEEL
qet_tb_generator-1.3.1.dist-info/entry_points.txt
qet_tb_generator-1.3.1.dist-info/top_level.txt
qet_tb_generator-1.3.1.dist-info/RECORD
